LavaAPI/LavaAPI.py
LavaAPI/__init__.py
LavaAPI-2.0.dist-info/METADATA
LavaAPI-2.0.dist-info/WHEEL
LavaAPI-2.0.dist-info/top_level.txt
LavaAPI-2.0.dist-info/RECORD
