Metadata-Version: 2.1
Name: LavaAPI
Version: 2.0
Summary: A simple library for accepting payments and using the LAVA Wallet
Home-page: https://github.com/billiedark/LavaAPI
Author: billiedark
Author-email: hhxx213@gmail.com
License: UNKNOWN
Platform: UNKNOWN
Classifier: Programming Language :: Python :: 3
Classifier: License :: OSI Approved :: MIT License
Classifier: Operating System :: OS Independent
Requires-Python: >=3.6
